GradescopeBase/Autograder.py
GradescopeBase/AutograderErrors.py
GradescopeBase/AutograderLeaderboard.py
GradescopeBase/AutograderRateLimit.py
GradescopeBase/AutograderSetup.py
GradescopeBase/AutograderState.py
GradescopeBase/AutograderSubTest.py
GradescopeBase/AutograderTeardown.py
GradescopeBase/AutograderTest.py
GradescopeBase/Timeout.py
GradescopeBase/Utils.py
GradescopeBase/VERSION
GradescopeBase/Visibility.py
GradescopeBase/__init__.py
GradescopeBase/autograder_utils/__init__.py
GradescopeBase/autograder_utils/decorators.py
GradescopeBase/autograder_utils/files.py
GradescopeBase/autograder_utils/json_test_runner.py
GradescopeBase-0.0.4.8.dist-info/METADATA
GradescopeBase-0.0.4.8.dist-info/WHEEL
GradescopeBase-0.0.4.8.dist-info/top_level.txt
GradescopeBase-0.0.4.8.dist-info/RECORD
